setup.py
riakcached/__init__.py
riakcached/clients.py
riakcached/exceptions.py
riakcached/pools.py
riakcached.egg-info/PKG-INFO
riakcached.egg-info/SOURCES.txt
riakcached.egg-info/dependency_links.txt
riakcached.egg-info/requires.txt
riakcached.egg-info/top_level.txt
riakcached/tests/__init__.py
riakcached/tests/test_pool.py
riakcached/tests/test_riakclient.py
riakcached/tests/test_threadedriakclient.py
riakcached/tests/test_urllib3pool.py