Metadata-Version: 1.0
Name: riakcached
Version: 0.1.0
Summary: A Memcached like interface to Riak
Home-page: https://github.com/brettlangdon/riakcached
Author: Brett Langdon
Author-email: brett@blangdon.com
License: MIT
Platform: UNKNOWN
Classifier: Intended Audience :: Developers
Classifier: Programming Language :: Python
Classifier: Programming Language :: Python :: 2.6
Classifier: Programming Language :: Python :: 2.7
Classifier: License :: OSI Approved :: MIT License
Classifier: Topic :: Database
